{
    "DOWN": {
        "precision": 0.528957528957529,
        "recall": 0.44336569579288027,
        "f1-score": 0.4823943661971831,
        "support": 309
    },
    "UP": {
        "precision": 0.4304635761589404,
        "recall": 0.5158730158730159,
        "f1-score": 0.4693140794223827,
        "support": 252
    },
    "accuracy": 0.47593582887700536,
    "macro avg": {
        "precision": 0.4797105525582347,
        "recall": 0.4796193558329481,
        "f1-score": 0.4758542228097829,
        "support": 561
    },
    "weighted avg": {
        "precision": 0.48471425604265495,
        "recall": 0.47593582887700536,
        "f1-score": 0.4765187293571659,
        "support": 561
    }
}