{
    "DOWN": {
        "precision": 0.6614035087719298,
        "recall": 0.5703479576399395,
        "f1-score": 0.6125101543460602,
        "support": 2644
    },
    "UP": {
        "precision": 0.3523375142531357,
        "recall": 0.4446043165467626,
        "f1-score": 0.39312977099236635,
        "support": 1390
    },
    "accuracy": 0.5270203272186416,
    "macro avg": {
        "precision": 0.5068705115125327,
        "recall": 0.507476137093351,
        "f1-score": 0.5028199626692132,
        "support": 4034
    },
    "weighted avg": {
        "precision": 0.5549082850780468,
        "recall": 0.5270203272186416,
        "f1-score": 0.5369180044051494,
        "support": 4034
    }
}