{
    "DOWN": {
        "precision": 0.85,
        "recall": 0.2924731182795699,
        "f1-score": 0.4352,
        "support": 2325
    },
    "UP": {
        "precision": 0.10109289617486339,
        "recall": 0.6065573770491803,
        "f1-score": 0.17330210772833723,
        "support": 305
    },
    "accuracy": 0.3288973384030418,
    "macro avg": {
        "precision": 0.4755464480874317,
        "recall": 0.4495152476643751,
        "f1-score": 0.3042510538641686,
        "support": 2630
    },
    "weighted avg": {
        "precision": 0.763149556400507,
        "recall": 0.3288973384030418,
        "f1-score": 0.40482781097229764,
        "support": 2630
    }
}