{
    "DOWN": {
        "precision": 0.8546910755148741,
        "recall": 0.45646196150320806,
        "f1-score": 0.5951005775741884,
        "support": 3273
    },
    "UP": {
        "precision": 0.27653517690117935,
        "recall": 0.728051391862955,
        "f1-score": 0.4008252284114353,
        "support": 934
    },
    "accuracy": 0.5167577846446398,
    "macro avg": {
        "precision": 0.5656131262080267,
        "recall": 0.5922566766830815,
        "f1-score": 0.4979629029928119,
        "support": 4207
    },
    "weighted avg": {
        "precision": 0.7263341443750617,
        "recall": 0.5167577846446398,
        "f1-score": 0.551969325822819,
        "support": 4207
    }
}