{
    "DOWN": {
        "precision": 0.8140350877192982,
        "recall": 0.4150268336314848,
        "f1-score": 0.5497630331753555,
        "support": 559
    },
    "UP": {
        "precision": 0.2517162471395881,
        "recall": 0.6748466257668712,
        "f1-score": 0.3666666666666667,
        "support": 163
    },
    "accuracy": 0.47368421052631576,
    "macro avg": {
        "precision": 0.5328756674294431,
        "recall": 0.544936729699178,
        "f1-score": 0.4582148499210111,
        "support": 722
    },
    "weighted avg": {
        "precision": 0.687084989361275,
        "recall": 0.47368421052631576,
        "f1-score": 0.5084268728693773,
        "support": 722
    }
}