{
    "DOWN": {
        "precision": 0.7706806282722513,
        "recall": 0.44864370618713806,
        "f1-score": 0.5671354267000577,
        "support": 3281
    },
    "UP": {
        "precision": 0.217560553633218,
        "recall": 0.5345377258235919,
        "f1-score": 0.3092529972333231,
        "support": 941
    },
    "accuracy": 0.46778777830412127,
    "macro avg": {
        "precision": 0.49412059095273464,
        "recall": 0.49159071600536497,
        "f1-score": 0.4381942119666904,
        "support": 4222
    },
    "weighted avg": {
        "precision": 0.6474011421909319,
        "recall": 0.46778777830412127,
        "f1-score": 0.5096585517289072,
        "support": 4222
    }
}