{
    "DOWN": {
        "precision": 0.7641119779715466,
        "recall": 0.4959785522788204,
        "f1-score": 0.6015173410404624,
        "support": 3357
    },
    "UP": {
        "precision": 0.2565905096660808,
        "recall": 0.5318761384335154,
        "f1-score": 0.34617664493183165,
        "support": 1098
    },
    "accuracy": 0.5048260381593714,
    "macro avg": {
        "precision": 0.5103512438188137,
        "recall": 0.5139273453561679,
        "f1-score": 0.473846992986147,
        "support": 4455
    },
    "weighted avg": {
        "precision": 0.6390258787124218,
        "recall": 0.5048260381593714,
        "f1-score": 0.538584886646012,
        "support": 4455
    }
}