{
    "DOWN": {
        "precision": 0.7062818336162988,
        "recall": 0.6720516962843296,
        "f1-score": 0.6887417218543047,
        "support": 619
    },
    "UP": {
        "precision": 0.39762611275964393,
        "recall": 0.4364820846905538,
        "f1-score": 0.41614906832298143,
        "support": 307
    },
    "accuracy": 0.593952483801296,
    "macro avg": {
        "precision": 0.5519539731879713,
        "recall": 0.5542668904874417,
        "f1-score": 0.5524453950886431,
        "support": 926
    },
    "weighted avg": {
        "precision": 0.6039521291854207,
        "recall": 0.593952483801296,
        "f1-score": 0.5983681315366846,
        "support": 926
    }
}