{
    "DOWN": {
        "precision": 0.7817531305903399,
        "recall": 0.15937272064186725,
        "f1-score": 0.2647682520448349,
        "support": 2742
    },
    "UP": {
        "precision": 0.052999178307313065,
        "recall": 0.5139442231075697,
        "f1-score": 0.09608938547486034,
        "support": 251
    },
    "accuracy": 0.18910791847644504,
    "macro avg": {
        "precision": 0.4173761544488265,
        "recall": 0.3366584718747185,
        "f1-score": 0.18042881875984762,
        "support": 2993
    },
    "weighted avg": {
        "precision": 0.7206381148793343,
        "recall": 0.18910791847644504,
        "f1-score": 0.2506224466625884,
        "support": 2993
    }
}