{
    "DOWN": {
        "precision": 0.673469387755102,
        "recall": 0.44594594594594594,
        "f1-score": 0.5365853658536585,
        "support": 222
    },
    "UP": {
        "precision": 0.36923076923076925,
        "recall": 0.6,
        "f1-score": 0.4571428571428572,
        "support": 120
    },
    "accuracy": 0.5,
    "macro avg": {
        "precision": 0.5213500784929357,
        "recall": 0.522972972972973,
        "f1-score": 0.4968641114982578,
        "support": 342
    },
    "weighted avg": {
        "precision": 0.5667189952904239,
        "recall": 0.5,
        "f1-score": 0.5087108013937282,
        "support": 342
    }
}