{
    "DOWN": {
        "precision": 0.8541979010494752,
        "recall": 0.6558273381294965,
        "f1-score": 0.7419827445873353,
        "support": 3475
    },
    "UP": {
        "precision": 0.2010688042752171,
        "recall": 0.43623188405797103,
        "f1-score": 0.2752629172382259,
        "support": 690
    },
    "accuracy": 0.6194477791116446,
    "macro avg": {
        "precision": 0.5276333526623461,
        "recall": 0.5460296110937337,
        "f1-score": 0.5086228309127806,
        "support": 4165
    },
    "weighted avg": {
        "precision": 0.7459964420400543,
        "recall": 0.6194477791116446,
        "f1-score": 0.664663013285802,
        "support": 4165
    }
}