{
    "DOWN": {
        "precision": 0.7374005305039788,
        "recall": 0.49554367201426025,
        "f1-score": 0.5927505330490405,
        "support": 561
    },
    "UP": {
        "precision": 0.33568075117370894,
        "recall": 0.5909090909090909,
        "f1-score": 0.4281437125748504,
        "support": 242
    },
    "accuracy": 0.5242839352428393,
    "macro avg": {
        "precision": 0.5365406408388439,
        "recall": 0.5432263814616756,
        "f1-score": 0.5104471228119454,
        "support": 803
    },
    "weighted avg": {
        "precision": 0.6163342956373221,
        "recall": 0.5242839352428393,
        "f1-score": 0.5431429981116134,
        "support": 803
    }
}