{
    "DOWN": {
        "precision": 0.6253776435045317,
        "recall": 0.32192846034214617,
        "f1-score": 0.4250513347022587,
        "support": 643
    },
    "UP": {
        "precision": 0.310126582278481,
        "recall": 0.6125,
        "f1-score": 0.411764705882353,
        "support": 320
    },
    "accuracy": 0.4184839044652129,
    "macro avg": {
        "precision": 0.46775211289150637,
        "recall": 0.4672142301710731,
        "f1-score": 0.41840802029230584,
        "support": 963
    },
    "weighted avg": {
        "precision": 0.5206213199403197,
        "recall": 0.4184839044652129,
        "f1-score": 0.4206362555513036,
        "support": 963
    }
}