{
    "DOWN": {
        "precision": 0.7922222222222223,
        "recall": 0.45970341715022567,
        "f1-score": 0.5818033455732355,
        "support": 3102
    },
    "UP": {
        "precision": 0.2709873858199217,
        "recall": 0.6248746238716149,
        "f1-score": 0.3780339805825243,
        "support": 997
    },
    "accuracy": 0.49987801902903145,
    "macro avg": {
        "precision": 0.531604804021072,
        "recall": 0.5422890205109203,
        "f1-score": 0.4799186630778799,
        "support": 4099
    },
    "weighted avg": {
        "precision": 0.6654422437169542,
        "recall": 0.49987801902903145,
        "f1-score": 0.5322405114927917,
        "support": 4099
    }
}