{
    "DOWN": {
        "precision": 0.6191222570532915,
        "recall": 0.9038901601830663,
        "f1-score": 0.7348837209302326,
        "support": 437
    },
    "UP": {
        "precision": 0.4166666666666667,
        "recall": 0.10989010989010989,
        "f1-score": 0.1739130434782609,
        "support": 273
    },
    "accuracy": 0.5985915492957746,
    "macro avg": {
        "precision": 0.5178944618599791,
        "recall": 0.5068901350365881,
        "f1-score": 0.4543983822042467,
        "support": 710
    },
    "weighted avg": {
        "precision": 0.54127665680604,
        "recall": 0.5985915492957746,
        "f1-score": 0.519186544952221,
        "support": 710
    }
}