{
    "DOWN": {
        "precision": 0.540381791483113,
        "recall": 0.4482338611449452,
        "f1-score": 0.49001331557922767,
        "support": 1642
    },
    "UP": {
        "precision": 0.45057610673135234,
        "recall": 0.5427319211102994,
        "f1-score": 0.4923790589794566,
        "support": 1369
    },
    "accuracy": 0.4911989372301561,
    "macro avg": {
        "precision": 0.49547894910723267,
        "recall": 0.49548289112762234,
        "f1-score": 0.4911961872793421,
        "support": 3011
    },
    "weighted avg": {
        "precision": 0.4995501799171348,
        "recall": 0.4911989372301561,
        "f1-score": 0.49108893919759816,
        "support": 3011
    }
}