{
    "DOWN": {
        "precision": 0.8172362555720654,
        "recall": 0.7352941176470589,
        "f1-score": 0.7741027445460944,
        "support": 748
    },
    "UP": {
        "precision": 0.41935483870967744,
        "recall": 0.5375939849624061,
        "f1-score": 0.471169686985173,
        "support": 266
    },
    "accuracy": 0.6834319526627219,
    "macro avg": {
        "precision": 0.6182955471408714,
        "recall": 0.6364440513047325,
        "f1-score": 0.6226362157656337,
        "support": 1014
    },
    "weighted avg": {
        "precision": 0.712861051543076,
        "recall": 0.6834319526627219,
        "f1-score": 0.6946350982825785,
        "support": 1014
    }
}