{
    "DOWN": {
        "precision": 0.6746031746031746,
        "recall": 0.1828612405880244,
        "f1-score": 0.2877291960507758,
        "support": 2789
    },
    "UP": {
        "precision": 0.279481504900411,
        "recall": 0.7823008849557522,
        "f1-score": 0.4118332168646634,
        "support": 1130
    },
    "accuracy": 0.35570298545547335,
    "macro avg": {
        "precision": 0.47704233975179283,
        "recall": 0.4825810627718883,
        "f1-score": 0.3497812064577196,
        "support": 3919
    },
    "weighted avg": {
        "precision": 0.5606742420274863,
        "recall": 0.35570298545547335,
        "f1-score": 0.32351320817623963,
        "support": 3919
    }
}