{
    "DOWN": {
        "precision": 0.5902140672782875,
        "recall": 0.3225267379679144,
        "f1-score": 0.41711692241193,
        "support": 2992
    },
    "UP": {
        "precision": 0.1930732484076433,
        "recall": 0.4199134199134199,
        "f1-score": 0.26452140714480504,
        "support": 1155
    },
    "accuracy": 0.34965034965034963,
    "macro avg": {
        "precision": 0.3916436578429654,
        "recall": 0.37122007894066716,
        "f1-score": 0.3408191647783675,
        "support": 4147
    },
    "weighted avg": {
        "precision": 0.4796045553912381,
        "recall": 0.34965034965034963,
        "f1-score": 0.3746168452155159,
        "support": 4147
    }
}