{
    "DOWN": {
        "precision": 0.7307692307692307,
        "recall": 0.6375,
        "f1-score": 0.6809557273366128,
        "support": 1520
    },
    "UP": {
        "precision": 0.38020247469066365,
        "recall": 0.48633093525179855,
        "f1-score": 0.4267676767676768,
        "support": 695
    },
    "accuracy": 0.5900677200902934,
    "macro avg": {
        "precision": 0.5554858527299472,
        "recall": 0.5619154676258993,
        "f1-score": 0.5538617020521448,
        "support": 2215
    },
    "weighted avg": {
        "precision": 0.6207719867626375,
        "recall": 0.5900677200902934,
        "f1-score": 0.6011992058262695,
        "support": 2215
    }
}