{
    "DOWN": {
        "precision": 0.6271097046413502,
        "recall": 0.6395911780527165,
        "f1-score": 0.6332889480692411,
        "support": 1859
    },
    "UP": {
        "precision": 0.4117647058823529,
        "recall": 0.39880952380952384,
        "f1-score": 0.40518358531317494,
        "support": 1176
    },
    "accuracy": 0.5462932454695223,
    "macro avg": {
        "precision": 0.5194372052618516,
        "recall": 0.5192003509311202,
        "f1-score": 0.519236266691208,
        "support": 3035
    },
    "weighted avg": {
        "precision": 0.543667952239182,
        "recall": 0.5462932454695223,
        "f1-score": 0.5449028173934145,
        "support": 3035
    }
}