{
    "DOWN": {
        "precision": 0.9592261904761905,
        "recall": 0.783041788143829,
        "f1-score": 0.8622257891920814,
        "support": 4116
    },
    "UP": {
        "precision": 0.2476832350463353,
        "recall": 0.6821345707656613,
        "f1-score": 0.36341161928306553,
        "support": 431
    },
    "accuracy": 0.7734770178139433,
    "macro avg": {
        "precision": 0.603454712761263,
        "recall": 0.7325881794547451,
        "f1-score": 0.6128187042375735,
        "support": 4547
    },
    "weighted avg": {
        "precision": 0.8917806189366551,
        "recall": 0.7734770178139433,
        "f1-score": 0.8149443053058298,
        "support": 4547
    }
}