{
    "DOWN": {
        "precision": 0.7485286249331193,
        "recall": 0.561171279582832,
        "f1-score": 0.6414488766620817,
        "support": 2493
    },
    "UP": {
        "precision": 0.3766381766381766,
        "recall": 0.5844385499557914,
        "f1-score": 0.4580734580734581,
        "support": 1131
    },
    "accuracy": 0.5684326710816777,
    "macro avg": {
        "precision": 0.562583400785648,
        "recall": 0.5728049147693117,
        "f1-score": 0.5497611673677699,
        "support": 3624
    },
    "weighted avg": {
        "precision": 0.6324667880066347,
        "recall": 0.5684326710816777,
        "f1-score": 0.5842199587747381,
        "support": 3624
    }
}