{
    "DOWN": {
        "precision": 0.6877192982456141,
        "recall": 0.29518072289156627,
        "f1-score": 0.4130663856691254,
        "support": 664
    },
    "UP": {
        "precision": 0.34269662921348315,
        "recall": 0.7327327327327328,
        "f1-score": 0.4669856459330144,
        "support": 333
    },
    "accuracy": 0.44132397191574724,
    "macro avg": {
        "precision": 0.5152079637295486,
        "recall": 0.5139567278121495,
        "f1-score": 0.4400260158010699,
        "support": 997
    },
    "weighted avg": {
        "precision": 0.5724810346671793,
        "recall": 0.44132397191574724,
        "f1-score": 0.4310755267602739,
        "support": 997
    }
}