{
    "DOWN": {
        "precision": 0.7366071428571429,
        "recall": 0.6021897810218978,
        "f1-score": 0.6626506024096386,
        "support": 274
    },
    "UP": {
        "precision": 0.31446540880503143,
        "recall": 0.45871559633027525,
        "f1-score": 0.373134328358209,
        "support": 109
    },
    "accuracy": 0.5613577023498695,
    "macro avg": {
        "precision": 0.5255362758310872,
        "recall": 0.5304526886760865,
        "f1-score": 0.5178924653839238,
        "support": 383
    },
    "weighted avg": {
        "precision": 0.6164675893018423,
        "recall": 0.5613577023498695,
        "f1-score": 0.5802556314654981,
        "support": 383
    }
}