{
    "DOWN": {
        "precision": 0.7496,
        "recall": 0.6661926768574475,
        "f1-score": 0.7054394880481837,
        "support": 2813
    },
    "UP": {
        "precision": 0.41495327102803736,
        "recall": 0.5154798761609907,
        "f1-score": 0.45978598550224364,
        "support": 1292
    },
    "accuracy": 0.6187576126674786,
    "macro avg": {
        "precision": 0.5822766355140188,
        "recall": 0.5908362765092191,
        "f1-score": 0.5826127367752136,
        "support": 4105
    },
    "weighted avg": {
        "precision": 0.6442739162407368,
        "recall": 0.6187576126674786,
        "f1-score": 0.6281229654441997,
        "support": 4105
    }
}