{
    "DOWN": {
        "precision": 0.7555163283318623,
        "recall": 0.2743589743589744,
        "f1-score": 0.40253938396426053,
        "support": 3120
    },
    "UP": {
        "precision": 0.20253610426206411,
        "recall": 0.6748826291079812,
        "f1-score": 0.3115686805743701,
        "support": 852
    },
    "accuracy": 0.36027190332326287,
    "macro avg": {
        "precision": 0.47902621629696324,
        "recall": 0.4746208017334778,
        "f1-score": 0.3570540322693153,
        "support": 3972
    },
    "weighted avg": {
        "precision": 0.6369012349513316,
        "recall": 0.36027190332326287,
        "f1-score": 0.3830260306691481,
        "support": 3972
    }
}