{
    "DOWN": {
        "precision": 0.697138869504536,
        "recall": 0.39008199921905506,
        "f1-score": 0.500250375563345,
        "support": 2561.0
    },
    "UP": {
        "precision": 0.31760594145915244,
        "recall": 0.6261843238587425,
        "f1-score": 0.4214492753623188,
        "support": 1161.0
    },
    "accuracy": 0.46372917786136486,
    "macro avg": {
        "precision": 0.5073724054818443,
        "recall": 0.5081331615388988,
        "f1-score": 0.4608498254628319,
        "support": 3722.0
    },
    "weighted avg": {
        "precision": 0.5787515160760862,
        "recall": 0.46372917786136486,
        "f1-score": 0.4756700216317513,
        "support": 3722.0
    }
}