{
    "DOWN": {
        "precision": 0.7362177250523377,
        "recall": 0.4563148788927336,
        "f1-score": 0.5634178905206942,
        "support": 2312.0
    },
    "UP": {
        "precision": 0.31610446137105547,
        "recall": 0.6058394160583942,
        "f1-score": 0.41544511977118337,
        "support": 959.0
    },
    "accuracy": 0.5001528584530724,
    "macro avg": {
        "precision": 0.5261610932116966,
        "recall": 0.5310771474755639,
        "f1-score": 0.4894315051459388,
        "support": 3271.0
    },
    "weighted avg": {
        "precision": 0.6130478626645818,
        "recall": 0.5001528584530724,
        "f1-score": 0.5200348617378202,
        "support": 3271.0
    }
}