{
    "DOWN": {
        "precision": 0.9061063690085358,
        "recall": 0.36829463570856685,
        "f1-score": 0.523719165085389,
        "support": 3747
    },
    "UP": {
        "precision": 0.10102544625902013,
        "recall": 0.6503667481662592,
        "f1-score": 0.17488494411571337,
        "support": 409
    },
    "accuracy": 0.3960538979788258,
    "macro avg": {
        "precision": 0.503565907633778,
        "recall": 0.509330691937413,
        "f1-score": 0.3493020546005512,
        "support": 4156
    },
    "weighted avg": {
        "precision": 0.826876797929481,
        "recall": 0.3960538979788258,
        "f1-score": 0.48938971456166486,
        "support": 4156
    }
}