{
    "DOWN": {
        "precision": 0.7125081859855926,
        "recall": 0.45220282626766417,
        "f1-score": 0.5532672260361048,
        "support": 2406
    },
    "UP": {
        "precision": 0.31991744066047473,
        "recall": 0.5854579792256847,
        "f1-score": 0.4137470804137471,
        "support": 1059
    },
    "accuracy": 0.49292929292929294,
    "macro avg": {
        "precision": 0.5162128133230337,
        "recall": 0.5188304027466744,
        "f1-score": 0.48350715322492593,
        "support": 3465
    },
    "weighted avg": {
        "precision": 0.5925215772412059,
        "recall": 0.49292929292929294,
        "f1-score": 0.5106260040407002,
        "support": 3465
    }
}