{
    "DOWN": {
        "precision": 0.6835443037974683,
        "recall": 0.4576271186440678,
        "f1-score": 0.5482233502538071,
        "support": 118
    },
    "UP": {
        "precision": 0.2808988764044944,
        "recall": 0.5,
        "f1-score": 0.3597122302158274,
        "support": 50
    },
    "accuracy": 0.47023809523809523,
    "macro avg": {
        "precision": 0.48222159010098137,
        "recall": 0.4788135593220339,
        "f1-score": 0.45396779023481726,
        "support": 168
    },
    "weighted avg": {
        "precision": 0.563709355168607,
        "recall": 0.47023809523809523,
        "f1-score": 0.4921188502425037,
        "support": 168
    }
}