{
    "DOWN": {
        "precision": 0.7131578947368421,
        "recall": 0.5334645669291339,
        "f1-score": 0.6103603603603605,
        "support": 1016
    },
    "UP": {
        "precision": 0.38917525773195877,
        "recall": 0.5807692307692308,
        "f1-score": 0.4660493827160494,
        "support": 520
    },
    "accuracy": 0.5494791666666666,
    "macro avg": {
        "precision": 0.5511665762344005,
        "recall": 0.5571168988491824,
        "f1-score": 0.538204871538205,
        "support": 1536
    },
    "weighted avg": {
        "precision": 0.6034762728341473,
        "recall": 0.5494791666666666,
        "f1-score": 0.5615050814703594,
        "support": 1536
    }
}