{
    "DOWN": {
        "precision": 0.7809090909090909,
        "recall": 0.6795886075949367,
        "f1-score": 0.7267343485617596,
        "support": 1264
    },
    "UP": {
        "precision": 0.35096153846153844,
        "recall": 0.47608695652173916,
        "f1-score": 0.4040590405904059,
        "support": 460
    },
    "accuracy": 0.6252900232018561,
    "macro avg": {
        "precision": 0.5659353146853147,
        "recall": 0.5778377820583379,
        "f1-score": 0.5653966945760828,
        "support": 1724
    },
    "weighted avg": {
        "precision": 0.6661899063813216,
        "recall": 0.6252900232018561,
        "f1-score": 0.6406376886622105,
        "support": 1724
    }
}