{
    "DOWN": {
        "precision": 0.7639123102866779,
        "recall": 0.4265536723163842,
        "f1-score": 0.5474320241691844,
        "support": 1062
    },
    "UP": {
        "precision": 0.27413587604290823,
        "recall": 0.6216216216216216,
        "f1-score": 0.380479735318445,
        "support": 370
    },
    "accuracy": 0.47695530726256985,
    "macro avg": {
        "precision": 0.5190240931647931,
        "recall": 0.5240876469690029,
        "f1-score": 0.4639558797438147,
        "support": 1432
    },
    "weighted avg": {
        "precision": 0.6373639299303967,
        "recall": 0.47695530726256985,
        "f1-score": 0.5042949104298173,
        "support": 1432
    }
}