{
    "DOWN": {
        "precision": 0.8813936249073387,
        "recall": 0.6607390941928314,
        "f1-score": 0.7552802922026361,
        "support": 3599
    },
    "UP": {
        "precision": 0.23544145272385722,
        "recall": 0.5402298850574713,
        "f1-score": 0.3279546445704318,
        "support": 696
    },
    "accuracy": 0.6412107101280559,
    "macro avg": {
        "precision": 0.558417538815598,
        "recall": 0.6004844896251513,
        "f1-score": 0.541617468386534,
        "support": 4295
    },
    "weighted avg": {
        "precision": 0.776717789787501,
        "recall": 0.6412107101280559,
        "f1-score": 0.6860326435991404,
        "support": 4295
    }
}