{
    "DOWN": {
        "precision": 0.6529786003470214,
        "recall": 0.5297982167996246,
        "f1-score": 0.5849740932642488,
        "support": 2131
    },
    "UP": {
        "precision": 0.36015325670498083,
        "recall": 0.4845360824742268,
        "f1-score": 0.41318681318681316,
        "support": 1164
    },
    "accuracy": 0.5138088012139606,
    "macro avg": {
        "precision": 0.5065659285260011,
        "recall": 0.5071671496369257,
        "f1-score": 0.49908045322553096,
        "support": 3295
    },
    "weighted avg": {
        "precision": 0.5495343818343248,
        "recall": 0.5138088012139606,
        "f1-score": 0.5242880859774096,
        "support": 3295
    }
}