{
    "DOWN": {
        "precision": 0.6129032258064516,
        "recall": 0.4973821989528796,
        "f1-score": 0.5491329479768786,
        "support": 191
    },
    "UP": {
        "precision": 0.40372670807453415,
        "recall": 0.52,
        "f1-score": 0.45454545454545453,
        "support": 125
    },
    "accuracy": 0.5063291139240507,
    "macro avg": {
        "precision": 0.5083149669404929,
        "recall": 0.5086910994764398,
        "f1-score": 0.5018392012611665,
        "support": 316
    },
    "weighted avg": {
        "precision": 0.5301593501213576,
        "recall": 0.5063291139240507,
        "f1-score": 0.5117170091195115,
        "support": 316
    }
}