{
    "DOWN": {
        "precision": 0.7122969837587007,
        "recall": 0.37807881773399016,
        "f1-score": 0.4939662107803701,
        "support": 1624
    },
    "UP": {
        "precision": 0.35421994884910485,
        "recall": 0.6907730673316709,
        "f1-score": 0.4683009298393914,
        "support": 802
    },
    "accuracy": 0.4814509480626546,
    "macro avg": {
        "precision": 0.5332584663039027,
        "recall": 0.5344259425328305,
        "f1-score": 0.4811335703098808,
        "support": 2426
    },
    "weighted avg": {
        "precision": 0.593921970569296,
        "recall": 0.4814509480626546,
        "f1-score": 0.48548164552288253,
        "support": 2426
    }
}