{
    "DOWN": {
        "precision": 0.8338192419825073,
        "recall": 0.6190476190476191,
        "f1-score": 0.7105590062111802,
        "support": 462.0
    },
    "UP": {
        "precision": 0.4152823920265781,
        "recall": 0.6868131868131868,
        "f1-score": 0.5175983436853002,
        "support": 182.0
    },
    "accuracy": 0.6381987577639752,
    "macro avg": {
        "precision": 0.6245508170045427,
        "recall": 0.6529304029304029,
        "f1-score": 0.6140786749482402,
        "support": 644.0
    },
    "weighted avg": {
        "precision": 0.7155370887340925,
        "recall": 0.6381987577639752,
        "f1-score": 0.6560266450625619,
        "support": 644.0
    }
}