{
    "DOWN": {
        "precision": 0.6683168316831684,
        "recall": 0.4166666666666667,
        "f1-score": 0.5133079847908746,
        "support": 648.0
    },
    "UP": {
        "precision": 0.335676625659051,
        "recall": 0.5876923076923077,
        "f1-score": 0.4272930648769575,
        "support": 325.0
    },
    "accuracy": 0.473792394655704,
    "macro avg": {
        "precision": 0.5019967286711097,
        "recall": 0.5021794871794872,
        "f1-score": 0.47030052483391604,
        "support": 973.0
    },
    "weighted avg": {
        "precision": 0.557208849198237,
        "recall": 0.473792394655704,
        "f1-score": 0.48457741030780876,
        "support": 973.0
    }
}