{
    "DOWN": {
        "precision": 0.6204906204906205,
        "recall": 0.47884187082405344,
        "f1-score": 0.5405405405405406,
        "support": 1796.0
    },
    "UP": {
        "precision": 0.4313487241798299,
        "recall": 0.5744336569579288,
        "f1-score": 0.4927133934767523,
        "support": 1236.0
    },
    "accuracy": 0.5178100263852242,
    "macro avg": {
        "precision": 0.5259196723352252,
        "recall": 0.5266377638909912,
        "f1-score": 0.5166269670086464,
        "support": 3032.0
    },
    "weighted avg": {
        "precision": 0.5433866020736887,
        "recall": 0.5178100263852242,
        "f1-score": 0.5210437220145371,
        "support": 3032.0
    }
}