{
    "DOWN": {
        "precision": 0.8484238765928906,
        "recall": 0.48785190898573083,
        "f1-score": 0.61949069539667,
        "support": 2593.0
    },
    "UP": {
        "precision": 0.319672131147541,
        "recall": 0.7341176470588235,
        "f1-score": 0.4453961456102784,
        "support": 850.0
    },
    "accuracy": 0.5486494336334592,
    "macro avg": {
        "precision": 0.5840480038702158,
        "recall": 0.6109847780222772,
        "f1-score": 0.5324434205034743,
        "support": 3443.0
    },
    "weighted avg": {
        "precision": 0.7178868496894497,
        "recall": 0.5486494336334592,
        "f1-score": 0.5765106293733088,
        "support": 3443.0
    }
}