{
    "DOWN": {
        "precision": 0.8123306233062331,
        "recall": 0.5141509433962265,
        "f1-score": 0.6297268907563026,
        "support": 2332.0
    },
    "UP": {
        "precision": 0.36312535132096685,
        "recall": 0.6998916576381365,
        "f1-score": 0.47816432272390824,
        "support": 923.0
    },
    "accuracy": 0.5668202764976958,
    "macro avg": {
        "precision": 0.5877279873136,
        "recall": 0.6070213005171815,
        "f1-score": 0.5539456067401054,
        "support": 3255.0
    },
    "weighted avg": {
        "precision": 0.6849522927248503,
        "recall": 0.566820276497696,
        "f1-score": 0.5867492408964254,
        "support": 3255.0
    }
}