{
    "DOWN": {
        "precision": 0.90625,
        "recall": 0.5918367346938775,
        "f1-score": 0.7160493827160493,
        "support": 147
    },
    "UP": {
        "precision": 0.3877551020408163,
        "recall": 0.8085106382978723,
        "f1-score": 0.5241379310344828,
        "support": 47
    },
    "accuracy": 0.6443298969072165,
    "macro avg": {
        "precision": 0.6470025510204082,
        "recall": 0.700173686495875,
        "f1-score": 0.6200936568752661,
        "support": 194
    },
    "weighted avg": {
        "precision": 0.7806352566799916,
        "recall": 0.6443298969072165,
        "f1-score": 0.6695553712261854,
        "support": 194
    }
}