{
    "DOWN": {
        "precision": 0.7559645535105658,
        "recall": 0.33303303303303305,
        "f1-score": 0.46237231603085266,
        "support": 3330
    },
    "UP": {
        "precision": 0.09087187883749488,
        "recall": 0.38275862068965516,
        "f1-score": 0.1468739662586834,
        "support": 580
    },
    "accuracy": 0.3404092071611253,
    "macro avg": {
        "precision": 0.42341821617403036,
        "recall": 0.35789582686134414,
        "f1-score": 0.304623141144768,
        "support": 3910
    },
    "weighted avg": {
        "precision": 0.6573063050935886,
        "recall": 0.3404092071611253,
        "f1-score": 0.41557204931273034,
        "support": 3910
    }
}