{
    "DOWN": {
        "precision": 0.8489341983317887,
        "recall": 0.5216400911161732,
        "f1-score": 0.6462081128747795,
        "support": 3512
    },
    "UP": {
        "precision": 0.20152091254752852,
        "recall": 0.5653333333333334,
        "f1-score": 0.29712683952347585,
        "support": 750
    },
    "accuracy": 0.5293289535429376,
    "macro avg": {
        "precision": 0.5252275554396586,
        "recall": 0.5434867122247533,
        "f1-score": 0.4716674761991277,
        "support": 4262
    },
    "weighted avg": {
        "precision": 0.7350064732407059,
        "recall": 0.5293289535429376,
        "f1-score": 0.5847789821818002,
        "support": 4262
    }
}