{
    "DOWN": {
        "precision": 0.9101229895931883,
        "recall": 0.4915687276443536,
        "f1-score": 0.6383543463835435,
        "support": 1957
    },
    "UP": {
        "precision": 0.27898550724637683,
        "recall": 0.8020833333333334,
        "f1-score": 0.41397849462365593,
        "support": 480
    },
    "accuracy": 0.5527287648748461,
    "macro avg": {
        "precision": 0.5945542484197825,
        "recall": 0.6468260304888435,
        "f1-score": 0.5261664205035997,
        "support": 2437
    },
    "weighted avg": {
        "precision": 0.7858119549085475,
        "recall": 0.5527287648748461,
        "f1-score": 0.5941604978629255,
        "support": 2437
    }
}