{
    "DOWN": {
        "precision": 0.6522277227722773,
        "recall": 0.4384359400998336,
        "f1-score": 0.5243781094527363,
        "support": 1202
    },
    "UP": {
        "precision": 0.38858695652173914,
        "recall": 0.604225352112676,
        "f1-score": 0.4729878721058435,
        "support": 710
    },
    "accuracy": 0.5,
    "macro avg": {
        "precision": 0.5204073396470081,
        "recall": 0.5213306461062548,
        "f1-score": 0.4986829907792899,
        "support": 1912
    },
    "weighted avg": {
        "precision": 0.5543276474386569,
        "recall": 0.5,
        "f1-score": 0.5052949146220387,
        "support": 1912
    }
}