{
    "DOWN": {
        "precision": 0.875,
        "recall": 0.37731295253419145,
        "f1-score": 0.5272625070264193,
        "support": 3729
    },
    "UP": {
        "precision": 0.14695077149155034,
        "recall": 0.6655574043261231,
        "f1-score": 0.2407463135720734,
        "support": 601
    },
    "accuracy": 0.41732101616628176,
    "macro avg": {
        "precision": 0.5109753857457752,
        "recall": 0.5214351784301573,
        "f1-score": 0.38400441029924637,
        "support": 4330
    },
    "weighted avg": {
        "precision": 0.7739474396458248,
        "recall": 0.41732101616628176,
        "f1-score": 0.48749432405504245,
        "support": 4330
    }
}