{
    "DOWN": {
        "precision": 0.7536231884057971,
        "recall": 0.5445026178010471,
        "f1-score": 0.6322188449848025,
        "support": 191
    },
    "UP": {
        "precision": 0.423841059602649,
        "recall": 0.6530612244897959,
        "f1-score": 0.5140562248995983,
        "support": 98
    },
    "accuracy": 0.5813148788927336,
    "macro avg": {
        "precision": 0.588732124004223,
        "recall": 0.5987819211454215,
        "f1-score": 0.5731375349422004,
        "support": 289
    },
    "weighted avg": {
        "precision": 0.6417939544171863,
        "recall": 0.5813148788927336,
        "f1-score": 0.59214985962719,
        "support": 289
    }
}