{
    "DOWN": {
        "precision": 0.8179091688089117,
        "recall": 0.7104577595831782,
        "f1-score": 0.7604062935670185,
        "support": 2687
    },
    "UP": {
        "precision": 0.346218487394958,
        "recall": 0.4922341696535245,
        "f1-score": 0.40651208682782436,
        "support": 837
    },
    "accuracy": 0.6586265607264472,
    "macro avg": {
        "precision": 0.5820638281019348,
        "recall": 0.6013459646183514,
        "f1-score": 0.5834591901974214,
        "support": 3524
    },
    "weighted avg": {
        "precision": 0.7058759394265396,
        "recall": 0.6586265607264472,
        "f1-score": 0.6763513982660236,
        "support": 3524
    }
}