{
    "DOWN": {
        "precision": 0.7540816326530613,
        "recall": 0.424468696151637,
        "f1-score": 0.5431826534362367,
        "support": 3482
    },
    "UP": {
        "precision": 0.1876773408998784,
        "recall": 0.48994708994708996,
        "f1-score": 0.27139507620164127,
        "support": 945
    },
    "accuracy": 0.4384459001581206,
    "macro avg": {
        "precision": 0.47087948677646985,
        "recall": 0.4572078930493635,
        "f1-score": 0.407288864818939,
        "support": 4427
    },
    "weighted avg": {
        "precision": 0.6331753630106945,
        "recall": 0.4384459001581206,
        "f1-score": 0.48516610487362255,
        "support": 4427
    }
}