{
    "DOWN": {
        "precision": 0.8779971791255289,
        "recall": 0.5161691542288557,
        "f1-score": 0.650130548302872,
        "support": 2412
    },
    "UP": {
        "precision": 0.17642907551164433,
        "recall": 0.5910165484633569,
        "f1-score": 0.27173913043478265,
        "support": 423
    },
    "accuracy": 0.527336860670194,
    "macro avg": {
        "precision": 0.5272131273185866,
        "recall": 0.5535928513461064,
        "f1-score": 0.4609348393688273,
        "support": 2835
    },
    "weighted avg": {
        "precision": 0.7733187636656793,
        "recall": 0.527336860670194,
        "f1-score": 0.5936721462717602,
        "support": 2835
    }
}