{
    "DOWN": {
        "precision": 0.7711111111111111,
        "recall": 0.5388198757763976,
        "f1-score": 0.6343692870201098,
        "support": 644
    },
    "UP": {
        "precision": 0.325,
        "recall": 0.5813008130081301,
        "f1-score": 0.41690962099125367,
        "support": 246
    },
    "accuracy": 0.550561797752809,
    "macro avg": {
        "precision": 0.5480555555555555,
        "recall": 0.5600603443922638,
        "f1-score": 0.5256394540056817,
        "support": 890
    },
    "weighted avg": {
        "precision": 0.6478039950062422,
        "recall": 0.550561797752809,
        "f1-score": 0.5742624579829203,
        "support": 890
    }
}