{
    "DOWN": {
        "precision": 0.7685512367491166,
        "recall": 0.6712962962962963,
        "f1-score": 0.7166392092257001,
        "support": 648
    },
    "UP": {
        "precision": 0.4496124031007752,
        "recall": 0.5704918032786885,
        "f1-score": 0.5028901734104048,
        "support": 305
    },
    "accuracy": 0.6390346274921301,
    "macro avg": {
        "precision": 0.6090818199249459,
        "recall": 0.6208940497874924,
        "f1-score": 0.6097646913180524,
        "support": 953
    },
    "weighted avg": {
        "precision": 0.6664774232520083,
        "recall": 0.6390346274921301,
        "f1-score": 0.6482305461368595,
        "support": 953
    }
}