{
    "DOWN": {
        "precision": 0.9924363057324841,
        "recall": 0.6076041920545941,
        "f1-score": 0.7537414965986395,
        "support": 4103
    },
    "UP": {
        "precision": 0.024242424242424242,
        "recall": 0.6779661016949152,
        "f1-score": 0.046811000585137506,
        "support": 59
    },
    "accuracy": 0.6086016338298895,
    "macro avg": {
        "precision": 0.5083393649874541,
        "recall": 0.6427851468747547,
        "f1-score": 0.40027624859188854,
        "support": 4162
    },
    "weighted avg": {
        "precision": 0.9787113083735428,
        "recall": 0.6086016338298895,
        "f1-score": 0.7437201368521723,
        "support": 4162
    }
}