{
    "DOWN": {
        "precision": 0.6352941176470588,
        "recall": 0.4909090909090909,
        "f1-score": 0.5538461538461538,
        "support": 110
    },
    "UP": {
        "precision": 0.4766355140186916,
        "recall": 0.6219512195121951,
        "f1-score": 0.5396825396825397,
        "support": 82
    },
    "accuracy": 0.546875,
    "macro avg": {
        "precision": 0.5559648158328752,
        "recall": 0.556430155210643,
        "f1-score": 0.5467643467643467,
        "support": 192
    },
    "weighted avg": {
        "precision": 0.5675336723474436,
        "recall": 0.546875,
        "f1-score": 0.5477971102971102,
        "support": 192
    }
}