{
    "DOWN": {
        "precision": 0.660145332588038,
        "recall": 0.40542396155166494,
        "f1-score": 0.5023394300297747,
        "support": 2913.0
    },
    "UP": {
        "precision": 0.350093808630394,
        "recall": 0.6054510058403634,
        "f1-score": 0.44365192582025675,
        "support": 1541.0
    },
    "accuracy": 0.4746295464750786,
    "macro avg": {
        "precision": 0.505119570609216,
        "recall": 0.5054374836960142,
        "f1-score": 0.47299567792501573,
        "support": 4454.0
    },
    "weighted avg": {
        "precision": 0.5528733527005819,
        "recall": 0.4746295464750786,
        "f1-score": 0.4820346603874605,
        "support": 4454.0
    }
}