{
    "DOWN": {
        "precision": 0.994634473507713,
        "recall": 0.7307218526730722,
        "f1-score": 0.8424939639255788,
        "support": 4059.0
    },
    "UP": {
        "precision": 0.14274509803921567,
        "recall": 0.9191919191919192,
        "f1-score": 0.24711473183978272,
        "support": 198.0
    },
    "accuracy": 0.7394879022786,
    "macro avg": {
        "precision": 0.5686897857734643,
        "recall": 0.8249568859324957,
        "f1-score": 0.5448043478826807,
        "support": 4257.0
    },
    "weighted avg": {
        "precision": 0.9550117118580154,
        "recall": 0.7394879022786,
        "f1-score": 0.8148019066192627,
        "support": 4257.0
    }
}