{
    "DOWN": {
        "precision": 0.5882352941176471,
        "recall": 0.29023746701846964,
        "f1-score": 0.38869257950530034,
        "support": 1516
    },
    "UP": {
        "precision": 0.4208826695371367,
        "recall": 0.7174311926605504,
        "f1-score": 0.5305291723202171,
        "support": 1090
    },
    "accuracy": 0.4689178818112049,
    "macro avg": {
        "precision": 0.5045589818273919,
        "recall": 0.50383432983951,
        "f1-score": 0.45961087591275873,
        "support": 2606
    },
    "weighted avg": {
        "precision": 0.5182374580498205,
        "recall": 0.4689178818112049,
        "f1-score": 0.44801793874101,
        "support": 2606
    }
}