{
    "DOWN": {
        "precision": 0.6057692307692307,
        "recall": 0.6810810810810811,
        "f1-score": 0.6412213740458016,
        "support": 185
    },
    "UP": {
        "precision": 0.3516483516483517,
        "recall": 0.2807017543859649,
        "f1-score": 0.31219512195121946,
        "support": 114
    },
    "accuracy": 0.5284280936454849,
    "macro avg": {
        "precision": 0.4787087912087912,
        "recall": 0.480891417733523,
        "f1-score": 0.4767082479985105,
        "support": 299
    },
    "weighted avg": {
        "precision": 0.5088803337131096,
        "recall": 0.5284280936454849,
        "f1-score": 0.5157732377956934,
        "support": 299
    }
}