{
    "DOWN": {
        "precision": 0.7623261694058154,
        "recall": 0.45681818181818185,
        "f1-score": 0.571293225959261,
        "support": 1320
    },
    "UP": {
        "precision": 0.3151862464183381,
        "recall": 0.637065637065637,
        "f1-score": 0.4217252396166134,
        "support": 518
    },
    "accuracy": 0.5076169749727966,
    "macro avg": {
        "precision": 0.5387562079120768,
        "recall": 0.5469419094419095,
        "f1-score": 0.49650923278793724,
        "support": 1838
    },
    "weighted avg": {
        "precision": 0.6363095861046657,
        "recall": 0.5076169749727966,
        "f1-score": 0.5291407684372308,
        "support": 1838
    }
}