{
    "DOWN": {
        "precision": 0.6096491228070176,
        "recall": 0.17684478371501272,
        "f1-score": 0.27416173570019725,
        "support": 786
    },
    "UP": {
        "precision": 0.2520231213872832,
        "recall": 0.7100977198697068,
        "f1-score": 0.3720136518771331,
        "support": 307
    },
    "accuracy": 0.3266239707227813,
    "macro avg": {
        "precision": 0.4308361220971504,
        "recall": 0.4434712517923598,
        "f1-score": 0.3230876937886652,
        "support": 1093
    },
    "weighted avg": {
        "precision": 0.5091997335701846,
        "recall": 0.3266239707227813,
        "f1-score": 0.30164621718813805,
        "support": 1093
    }
}