{
    "DOWN": {
        "precision": 0.6918798665183538,
        "recall": 0.5786046511627907,
        "f1-score": 0.6301925025329281,
        "support": 1075
    },
    "UP": {
        "precision": 0.4243964421855146,
        "recall": 0.546644844517185,
        "f1-score": 0.4778254649499284,
        "support": 611
    },
    "accuracy": 0.5670225385527876,
    "macro avg": {
        "precision": 0.5581381543519341,
        "recall": 0.5626247478399878,
        "f1-score": 0.5540089837414283,
        "support": 1686
    },
    "weighted avg": {
        "precision": 0.5949448888983272,
        "recall": 0.5670225385527876,
        "f1-score": 0.5749752664930629,
        "support": 1686
    }
}