{
    "DOWN": {
        "precision": 0.7630208333333334,
        "recall": 0.4628751974723539,
        "f1-score": 0.576204523107178,
        "support": 633
    },
    "UP": {
        "precision": 0.28721174004192873,
        "recall": 0.6008771929824561,
        "f1-score": 0.38865248226950355,
        "support": 228
    },
    "accuracy": 0.4994192799070848,
    "macro avg": {
        "precision": 0.5251162866876311,
        "recall": 0.531876195227405,
        "f1-score": 0.48242850268834075,
        "support": 861
    },
    "weighted avg": {
        "precision": 0.6370226065383969,
        "recall": 0.4994192799070848,
        "f1-score": 0.5265391743139262,
        "support": 861
    }
}