{
    "DOWN": {
        "precision": 0.839882697947214,
        "recall": 0.5741780272654371,
        "f1-score": 0.6820671588473446,
        "support": 2494
    },
    "UP": {
        "precision": 0.19727891156462585,
        "recall": 0.4887640449438202,
        "f1-score": 0.2810985460420032,
        "support": 534
    },
    "accuracy": 0.5591149273447821,
    "macro avg": {
        "precision": 0.5185808047559199,
        "recall": 0.5314710361046286,
        "f1-score": 0.4815828524446739,
        "support": 3028
    },
    "weighted avg": {
        "precision": 0.7265569311280918,
        "recall": 0.5591149273447821,
        "f1-score": 0.6113547284516867,
        "support": 3028
    }
}