{
    "DOWN": {
        "precision": 0.6685962373371924,
        "recall": 0.33237410071942447,
        "f1-score": 0.4440172993753004,
        "support": 2780
    },
    "UP": {
        "precision": 0.2655322516818362,
        "recall": 0.5943312666076174,
        "f1-score": 0.3670678336980306,
        "support": 1129
    },
    "accuracy": 0.4080327449475569,
    "macro avg": {
        "precision": 0.46706424450951434,
        "recall": 0.4633526836635209,
        "f1-score": 0.4055425665366655,
        "support": 3909
    },
    "weighted avg": {
        "precision": 0.5521830268473236,
        "recall": 0.4080327449475569,
        "f1-score": 0.42179270312315464,
        "support": 3909
    }
}