{
    "DOWN": {
        "precision": 0.7553903345724907,
        "recall": 0.3761569788967049,
        "f1-score": 0.5022244191794365,
        "support": 2701
    },
    "UP": {
        "precision": 0.34841453982985304,
        "recall": 0.732520325203252,
        "f1-score": 0.47222222222222215,
        "support": 1230
    },
    "accuracy": 0.48766217247519716,
    "macro avg": {
        "precision": 0.5519024372011718,
        "recall": 0.5543386520499785,
        "f1-score": 0.4872233207008293,
        "support": 3931
    },
    "weighted avg": {
        "precision": 0.6280486333429196,
        "recall": 0.48766217247519716,
        "f1-score": 0.4928368073103514,
        "support": 3931
    }
}