{
    "DOWN": {
        "precision": 0.6692359249329759,
        "recall": 0.670359180933199,
        "f1-score": 0.6697970820057018,
        "support": 2979
    },
    "UP": {
        "precision": 0.3260123541523679,
        "recall": 0.32489740082079344,
        "f1-score": 0.3254539225762248,
        "support": 1462
    },
    "accuracy": 0.5566313893267282,
    "macro avg": {
        "precision": 0.49762413954267193,
        "recall": 0.4976282908769962,
        "f1-score": 0.49762550229096325,
        "support": 4441
    },
    "weighted avg": {
        "precision": 0.5562449633294522,
        "recall": 0.5566313893267282,
        "f1-score": 0.5564375460710259,
        "support": 4441
    }
}