{
    "DOWN": {
        "precision": 0.662992125984252,
        "recall": 0.3250965250965251,
        "f1-score": 0.4362694300518135,
        "support": 1295
    },
    "UP": {
        "precision": 0.32195500387897596,
        "recall": 0.6597774244833068,
        "f1-score": 0.4327424400417101,
        "support": 629
    },
    "accuracy": 0.43451143451143454,
    "macro avg": {
        "precision": 0.492473564931614,
        "recall": 0.49243697478991594,
        "f1-score": 0.4345059350467618,
        "support": 1924
    },
    "weighted avg": {
        "precision": 0.551499220680604,
        "recall": 0.43451143451143454,
        "f1-score": 0.43511637562543354,
        "support": 1924
    }
}