{
    "DOWN": {
        "precision": 0.7783868441660141,
        "recall": 0.35871526524720315,
        "f1-score": 0.49110671936758893,
        "support": 2771
    },
    "UP": {
        "precision": 0.10658622423328305,
        "recall": 0.42828282828282827,
        "f1-score": 0.1706924315619968,
        "support": 495
    },
    "accuracy": 0.3692590324556032,
    "macro avg": {
        "precision": 0.44248653419964856,
        "recall": 0.3934990467650157,
        "f1-score": 0.33089957546479287,
        "support": 3266
    },
    "weighted avg": {
        "precision": 0.6765677055050521,
        "recall": 0.3692590324556032,
        "f1-score": 0.4425442354533918,
        "support": 3266
    }
}