{
    "DOWN": {
        "precision": 0.8452579034941764,
        "recall": 0.21061359867330018,
        "f1-score": 0.3372054430799868,
        "support": 2412
    },
    "UP": {
        "precision": 0.1477170993733214,
        "recall": 0.7801418439716312,
        "f1-score": 0.24840045163718477,
        "support": 423
    },
    "accuracy": 0.2955908289241623,
    "macro avg": {
        "precision": 0.49648750143374887,
        "recall": 0.4953777213224657,
        "f1-score": 0.2928029473585858,
        "support": 2835
    },
    "weighted avg": {
        "precision": 0.7411803866888426,
        "recall": 0.2955908289241623,
        "f1-score": 0.3239551745155052,
        "support": 2835
    }
}