{
    "DOWN": {
        "precision": 0.9696176008381352,
        "recall": 0.46148092744951386,
        "f1-score": 0.6253378378378378,
        "support": 4011
    },
    "UP": {
        "precision": 0.05263157894736842,
        "recall": 0.6741573033707865,
        "f1-score": 0.09764035801464604,
        "support": 178
    },
    "accuracy": 0.4705180233946049,
    "macro avg": {
        "precision": 0.5111245898927518,
        "recall": 0.5678191154101502,
        "f1-score": 0.36148909792624195,
        "support": 4189
    },
    "weighted avg": {
        "precision": 0.9306528092657894,
        "recall": 0.4705180233946049,
        "f1-score": 0.6029147890413402,
        "support": 4189
    }
}