{
    "DOWN": {
        "precision": 0.834981247869076,
        "recall": 0.6776425013835086,
        "f1-score": 0.7481289140064152,
        "support": 3614
    },
    "UP": {
        "precision": 0.13511507052709726,
        "recall": 0.2732732732732733,
        "f1-score": 0.18082463984103328,
        "support": 666
    },
    "accuracy": 0.6147196261682243,
    "macro avg": {
        "precision": 0.48504815919808664,
        "recall": 0.4754578873283909,
        "f1-score": 0.46447677692372424,
        "support": 4280
    },
    "weighted avg": {
        "precision": 0.7260768380303475,
        "recall": 0.6147196261682243,
        "f1-score": 0.6598521274189983,
        "support": 4280
    }
}