{
    "DOWN": {
        "precision": 0.7088888888888889,
        "recall": 0.13551401869158877,
        "f1-score": 0.2275320970042796,
        "support": 2354
    },
    "UP": {
        "precision": 0.3200801871032409,
        "recall": 0.8797061524334252,
        "f1-score": 0.46937775600195975,
        "support": 1089
    },
    "accuracy": 0.3708974731338949,
    "macro avg": {
        "precision": 0.5144845379960649,
        "recall": 0.507610085562507,
        "f1-score": 0.34845492650311966,
        "support": 3443
    },
    "weighted avg": {
        "precision": 0.5859110566947063,
        "recall": 0.3708974731338949,
        "f1-score": 0.3040264108725554,
        "support": 3443
    }
}