{
    "DOWN": {
        "precision": 0.628140703517588,
        "recall": 0.5020080321285141,
        "f1-score": 0.5580357142857143,
        "support": 249
    },
    "UP": {
        "precision": 0.3439153439153439,
        "recall": 0.4676258992805755,
        "f1-score": 0.3963414634146341,
        "support": 139
    },
    "accuracy": 0.4896907216494845,
    "macro avg": {
        "precision": 0.4860280237164659,
        "recall": 0.4848169657045448,
        "f1-score": 0.47718858885017423,
        "support": 388
    },
    "weighted avg": {
        "precision": 0.5263177009796707,
        "recall": 0.4896907216494845,
        "f1-score": 0.5001091656489098,
        "support": 388
    }
}